pytorch_pfn_extras/__init__.py
pytorch_pfn_extras/_tensor.py
pytorch_pfn_extras/_torch_version.py
pytorch_pfn_extras/_version.py
pytorch_pfn_extras/config.py
pytorch_pfn_extras/config_types.py
pytorch_pfn_extras/engine.py
pytorch_pfn_extras/logging.py
pytorch_pfn_extras/py.typed
pytorch_pfn_extras/reporting.py
pytorch_pfn_extras/testing.py
pytorch_pfn_extras/torchscript.py
pytorch_pfn_extras/_cupy/__init__.py
pytorch_pfn_extras/_cupy/_cupy_stub.py
pytorch_pfn_extras/_dynamo/__init__.py
pytorch_pfn_extras/_dynamo/_compile.py
pytorch_pfn_extras/_dynamo/_optimizer.py
pytorch_pfn_extras/_dynamo/_splitter.py
pytorch_pfn_extras/cuda/__init__.py
pytorch_pfn_extras/cuda/_allocator.py
pytorch_pfn_extras/dataloaders/__init__.py
pytorch_pfn_extras/dataloaders/dataloader.py
pytorch_pfn_extras/dataloaders/utils.py
pytorch_pfn_extras/dataset/__init__.py
pytorch_pfn_extras/dataset/shared_dataset.py
pytorch_pfn_extras/dataset/tabular/__init__.py
pytorch_pfn_extras/dataset/tabular/_asmode.py
pytorch_pfn_extras/dataset/tabular/_concat.py
pytorch_pfn_extras/dataset/tabular/_join.py
pytorch_pfn_extras/dataset/tabular/_slice.py
pytorch_pfn_extras/dataset/tabular/_transform.py
pytorch_pfn_extras/dataset/tabular/_utils.py
pytorch_pfn_extras/dataset/tabular/_with_converter.py
pytorch_pfn_extras/dataset/tabular/delegate_dataset.py
pytorch_pfn_extras/dataset/tabular/from_data.py
pytorch_pfn_extras/dataset/tabular/tabular_dataset.py
pytorch_pfn_extras/distributed/__init__.py
pytorch_pfn_extras/distributed/_dataset_util.py
pytorch_pfn_extras/distributed/_distributed_validation_sampler.py
pytorch_pfn_extras/distributed/_initialize.py
pytorch_pfn_extras/handler/__init__.py
pytorch_pfn_extras/handler/_code_block.py
pytorch_pfn_extras/handler/_handler.py
pytorch_pfn_extras/handler/_logic.py
pytorch_pfn_extras/nn/__init__.py
pytorch_pfn_extras/nn/modules/__init__.py
pytorch_pfn_extras/nn/modules/ensure_shape.py
pytorch_pfn_extras/nn/modules/extended_sequential.py
pytorch_pfn_extras-0.8.4.dist-info/licenses/LICENSE
pytorch_pfn_extras-0.8.4.dist-info/METADATA
pytorch_pfn_extras-0.8.4.dist-info/WHEEL
pytorch_pfn_extras-0.8.4.dist-info/top_level.txt
pytorch_pfn_extras-0.8.4.dist-info/RECORD
