Metadata-Version: 2.4
Name: pytorch-pfn-extras
Version: 0.8.4
Summary: Supplementary components to accelerate research and development in PyTorch.
Author: Preferred Networks, Inc.
License: MIT License
Requires-Python: >=3.9.0
License-File: LICENSE
Requires-Dist: numpy
Requires-Dist: packaging
Requires-Dist: torch
Requires-Dist: typing-extensions>=3.10
Provides-Extra: onnx
Requires-Dist: onnx; extra == "onnx"
Dynamic: author
Dynamic: description
Dynamic: description-content-type
Dynamic: license
Dynamic: license-file
Dynamic: provides-extra
Dynamic: requires-dist
Dynamic: requires-python
Dynamic: summary
